publish/__init__.py
publish/checksum.py
publish/common.py
publish/publish.py
publish/publish_container.py
publish/signature.py
publish/cli/__init__.py
publish/cli/common.py
publish/cli/publish.py
publish/cli/return_codes.py
publish/cli/sign.py
publish/cli/verify.py
publish/utils/__init__.py
publish/utils/io.py
publish/utils/job.py
tests/__init__.py
tests/common.py
tests/test_image_publish.py
tests/test_publish.py
tests/test_publish_cli.py
tests/test_sign.py
tests/test_sign_cli.py
tests/test_verify.py
tests/test_verify_cli.py
publishing_tools-0.0.8.dist-info/METADATA
publishing_tools-0.0.8.dist-info/WHEEL
publishing_tools-0.0.8.dist-info/entry_points.txt
publishing_tools-0.0.8.dist-info/top_level.txt
publishing_tools-0.0.8.dist-info/RECORD
