Metadata-Version: 2.1
Name: publishing-tools
Version: 0.0.8
Summary: Tools that can be used for publishing/releasing packages and container images.
Home-page: https://github.com/rasmunk/publishing-tools
Author: Rasmus Munk
Author-email: munk1@live.dk
License: MIT
Keywords: Publishing,Signature,Checksum,Verification,Packages,Container Images
Classifier: Intended Audience :: Developers
Classifier: Intended Audience :: System Administrators
Classifier: Programming Language :: Python
Classifier: Programming Language :: Python :: 3.8
Classifier: Programming Language :: Python :: 3.9
Classifier: Programming Language :: Python :: 3.10
Classifier: Programming Language :: Python :: 3.11
Classifier: Programming Language :: Python :: 3.12
Requires-Dist: PyYAML>=6.0.1
Requires-Dist: podman>=5.1.0
Provides-Extra: dev
Requires-Dist: black==24.3.0; extra == "dev"
Requires-Dist: docutils==0.18.1; extra == "dev"
Requires-Dist: flake8==6.0.0; extra == "dev"
